{
  "_class": "text",
  "attributedString": {
    "_class": "attributedString",
    "attributes": [
      {
        "_class": "stringAttribute",
        "attributes": {
          "MSAttributedStringColorAttribute": {
            "_class": "color",
            "alpha": 1,
            "blue": 0.4470588235294117,
            "green": 0.4470588235294117,
            "red": 0.4470588235294117
          },
          "MSAttributedStringFontAttribute": {
            "_class": "fontDescriptor",
            "attributes": {
              "name": "Raleway-Regular",
              "size": 20
            }
          },
          "paragraphStyle": {
            "_class": "paragraphStyle"
          },
          "textStyleVerticalAlignmentKey": 0
        },
        "length": 10,
        "location": 0
      }
    ],
    "string": "100 people"
  },
  "automaticallyDrawOnUnderlyingPath": false,
  "booleanOperation": -1,
  "clippingMaskMode": 0,
  "do_objectID": "4C659D4B-BD90-48CF-9594-1F50FF360560",
  "dontSynchroniseWithSymbol": false,
  "exportOptions": {
    "_class": "exportOptions",
    "do_objectID": "CC695D4D-1405-4EEE-AF1D-A49F3B4C55C6",
    "exportFormats": [
    ],
    "includedLayerIds": [
    ],
    "layerOptions": 0,
    "shouldTrim": false
  },
  "frame": {
    "_class": "rect",
    "constrainProportions": false,
    "do_objectID": "C8FF3B92-3B86-431B-9EDE-A6AEF57F6E04",
    "height": 24,
    "width": 104,
    "x": 456,
    "y": 109
  },
  "glyphBounds": "{{0, 4}, {104, 20}}",
  "hasClippingMask": false,
  "isFixedToViewport": false,
  "isFlippedHorizontal": false,
  "isFlippedVertical": false,
  "isLocked": false,
  "isVisible": true,
  "layerListExpandedType": 0,
  "lineSpacingBehaviour": 2,
  "name": "100 people",
  "nameIsFixed": false,
  "resizingConstraint": 47,
  "resizingType": 0,
  "rotation": 0,
  "shouldBreakMaskChain": false,
  "style": {
    "_class": "style",
    "do_objectID": "87F93B00-3AFA-485D-852C-798B3E68CEBC",
    "endMarkerType": 0,
    "miterLimit": 10,
    "startMarkerType": 0,
    "textStyle": {
      "_class": "textStyle",
      "do_objectID": "058F4638-8E58-482F-B315-7471C682DBDC",
      "encodedAttributes": {
        "MSAttributedStringColorAttribute": {
          "_class": "color",
          "alpha": 1,
          "blue": 0.4470588235294117,
          "green": 0.4470588235294117,
          "red": 0.4470588235294117
        },
        "MSAttributedStringFontAttribute": {
          "_class": "fontDescriptor",
          "attributes": {
            "name": "Raleway-Regular",
            "size": 20
          }
        },
        "paragraphStyle": {
          "_class": "paragraphStyle"
        },
        "textStyleVerticalAlignmentKey": 0
      },
      "verticalAlignment": 0
    },
    "windingRule": 1
  },
  "textBehaviour": 0
}