{
  "_class": "text",
  "attributedString": {
    "_class": "attributedString",
    "attributes": [
      {
        "_class": "stringAttribute",
        "attributes": {
          "MSAttributedStringColorAttribute": {
            "_class": "color",
            "alpha": 1,
            "blue": 0.4470588235294117,
            "green": 0.4470588235294117,
            "red": 0.4470588235294117
          },
          "MSAttributedStringFontAttribute": {
            "_class": "fontDescriptor",
            "attributes": {
              "name": "Raleway-Bold",
              "size": 36
            }
          },
          "paragraphStyle": {
            "_class": "paragraphStyle"
          },
          "textStyleVerticalAlignmentKey": 0
        },
        "length": 37,
        "location": 0
      }
    ],
    "string": "Please fill in the necessary details…"
  },
  "automaticallyDrawOnUnderlyingPath": false,
  "booleanOperation": -1,
  "clippingMaskMode": 0,
  "do_objectID": "DAA69A2E-8ADB-4A9C-844D-BFFD647FC96C",
  "dontSynchroniseWithSymbol": false,
  "exportOptions": {
    "_class": "exportOptions",
    "do_objectID": "8635C89B-0407-4DF8-8C72-19FBDEC3A873",
    "exportFormats": [
    ],
    "includedLayerIds": [
    ],
    "layerOptions": 0,
    "shouldTrim": false
  },
  "frame": {
    "_class": "rect",
    "constrainProportions": false,
    "do_objectID": "30F1AE67-5EB9-492B-B158-0C4641D505A5",
    "height": 42,
    "width": 603,
    "x": 49,
    "y": 448
  },
  "glyphBounds": "{{2, 7}, {599, 36}}",
  "hasClippingMask": false,
  "isFixedToViewport": false,
  "isFlippedHorizontal": false,
  "isFlippedVertical": false,
  "isLocked": false,
  "isVisible": true,
  "layerListExpandedType": 0,
  "lineSpacingBehaviour": 2,
  "name": "Please fill in the n",
  "nameIsFixed": false,
  "resizingConstraint": 47,
  "resizingType": 0,
  "rotation": 0,
  "shouldBreakMaskChain": false,
  "style": {
    "_class": "style",
    "do_objectID": "7894CC82-F596-44F5-95A4-D914230CD44E",
    "endMarkerType": 0,
    "miterLimit": 10,
    "startMarkerType": 0,
    "textStyle": {
      "_class": "textStyle",
      "do_objectID": "5C35ABDC-9714-4203-B9D1-EF15DE49C9B6",
      "encodedAttributes": {
        "MSAttributedStringColorAttribute": {
          "_class": "color",
          "alpha": 1,
          "blue": 0.4470588235294117,
          "green": 0.4470588235294117,
          "red": 0.4470588235294117
        },
        "MSAttributedStringFontAttribute": {
          "_class": "fontDescriptor",
          "attributes": {
            "name": "Raleway-Bold",
            "size": 36
          }
        },
        "paragraphStyle": {
          "_class": "paragraphStyle"
        },
        "textStyleVerticalAlignmentKey": 0
      },
      "verticalAlignment": 0
    },
    "windingRule": 1
  },
  "textBehaviour": 0
}