{
  "_class": "symbolInstance",
  "booleanOperation": -1,
  "clippingMaskMode": 0,
  "do_objectID": "703F9CD6-9FBF-4D31-8EA8-4AA40BE1E592",
  "exportOptions": {
    "_class": "exportOptions",
    "do_objectID": "FDA59EE2-6548-4DFB-AFAC-2DF9B9838CC3",
    "exportFormats": [
    ],
    "includedLayerIds": [
    ],
    "layerOptions": 0,
    "shouldTrim": false
  },
  "frame": {
    "_class": "rect",
    "constrainProportions": false,
    "do_objectID": "04E84115-653A-4166-8CCC-BE3C982B029E",
    "height": 19,
    "width": 18,
    "x": 1314,
    "y": 947
  },
  "hasClippingMask": false,
  "horizontalSpacing": 0,
  "isFixedToViewport": false,
  "isFlippedHorizontal": false,
  "isFlippedVertical": false,
  "isLocked": false,
  "isVisible": true,
  "layerListExpandedType": 0,
  "name": "Radio / Checked",
  "nameIsFixed": false,
  "overrideValues": [
  ],
  "resizingConstraint": 63,
  "resizingType": 0,
  "rotation": 0,
  "scale": 1,
  "shouldBreakMaskChain": false,
  "style": {
    "_class": "style",
    "do_objectID": "D544E030-6D79-40F2-A1F7-85590F2CB9C3",
    "endMarkerType": 0,
    "miterLimit": 10,
    "startMarkerType": 0,
    "windingRule": 1
  },
  "symbolID": "1F107F35-E562-4EC4-9D4D-7D54FA0CB18B",
  "verticalSpacing": 0
}