{
  "_class": "group",
  "booleanOperation": -1,
  "clippingMaskMode": 0,
  "do_objectID": "BF5EFF08-E827-4DBF-A531-FA2954E78804",
  "exportOptions": {
    "_class": "exportOptions",
    "do_objectID": "CAAC49E6-1A1B-4B1F-9CA4-1DF78FBCAA25",
    "exportFormats": [
    ],
    "includedLayerIds": [
    ],
    "layerOptions": 0,
    "shouldTrim": false
  },
  "frame": {
    "_class": "rect",
    "constrainProportions": false,
    "do_objectID": "D08E4E65-922C-4925-B19D-ABCAF1C858DA",
    "height": 294,
    "width": 751,
    "x": 345,
    "y": 1346
  },
  "groupLayout": {
    "_class": "MSImmutableFreeformGroupLayout"
  },
  "hasClickThrough": false,
  "hasClippingMask": false,
  "isFixedToViewport": false,
  "isFlippedHorizontal": false,
  "isFlippedVertical": false,
  "isLocked": false,
  "isVisible": true,
  "layerListExpandedType": 0,
  "layers": [
    {
      "class": "group",
      "id": "57C8CBC9-D74A-4E3C-AF47-E27D4973664C"
    },
    {
      "class": "symbolInstance",
      "id": "06FEE22F-7A48-4C6E-A1D7-A3C442CED1CE"
    },
    {
      "class": "symbolInstance",
      "id": "04D48F1D-A241-481D-B298-6BC9BD273637"
    }
  ],
  "name": "Group 2",
  "nameIsFixed": false,
  "resizingConstraint": 63,
  "resizingType": 0,
  "rotation": 0,
  "shouldBreakMaskChain": false,
  "style": {
    "_class": "style",
    "do_objectID": "F54FDA29-0F1B-4189-829A-B9023A79226D",
    "endMarkerType": 0,
    "miterLimit": 10,
    "startMarkerType": 0,
    "windingRule": 1
  }
}