{
  "_class": "symbolInstance",
  "booleanOperation": -1,
  "clippingMaskMode": 0,
  "do_objectID": "1E76ABF8-D51C-4A1E-AC07-0E356E1A0E13",
  "exportOptions": {
    "_class": "exportOptions",
    "do_objectID": "85AC6202-8D7C-40F8-80F3-B587BA77A72E",
    "exportFormats": [
    ],
    "includedLayerIds": [
    ],
    "layerOptions": 0,
    "shouldTrim": false
  },
  "frame": {
    "_class": "rect",
    "constrainProportions": false,
    "do_objectID": "59608D56-C389-4A42-9783-D7B82149450A",
    "height": 57,
    "width": 356,
    "x": 14,
    "y": 253
  },
  "hasClippingMask": false,
  "horizontalSpacing": 0,
  "isFixedToViewport": false,
  "isFlippedHorizontal": false,
  "isFlippedVertical": false,
  "isLocked": false,
  "isVisible": true,
  "layerListExpandedType": 0,
  "name": "My Events / Events",
  "nameIsFixed": false,
  "overrideValues": [
  ],
  "resizingConstraint": 63,
  "resizingType": 0,
  "rotation": 0,
  "scale": 1,
  "shouldBreakMaskChain": false,
  "style": {
    "_class": "style",
    "do_objectID": "7F100C23-8114-456E-AACD-9D00EBFE8F33",
    "endMarkerType": 0,
    "miterLimit": 10,
    "startMarkerType": 0,
    "windingRule": 1
  },
  "symbolID": "9D825A79-6612-48F4-B180-B8650EE04AD7",
  "verticalSpacing": 0
}