{
  "_class": "shapePath",
  "booleanOperation": -1,
  "clippingMaskMode": 0,
  "do_objectID": "F5FCCE33-92FD-44B7-A653-C64AE170ECD8",
  "edited": true,
  "exportOptions": {
    "_class": "exportOptions",
    "do_objectID": "FC9BD037-CE00-4E0E-9ED2-F045A6ABCEC0",
    "exportFormats": [
    ],
    "includedLayerIds": [
    ],
    "layerOptions": 0,
    "shouldTrim": false
  },
  "frame": {
    "_class": "rect",
    "constrainProportions": false,
    "do_objectID": "2A2C7DF1-6569-43DB-8B98-1B7D783835CA",
    "height": 3.337000000000003,
    "width": 4.532999999999987,
    "x": 8,
    "y": 17.54900000000001
  },
  "hasClippingMask": false,
  "isClosed": true,
  "isFixedToViewport": false,
  "isFlippedHorizontal": false,
  "isFlippedVertical": false,
  "isLocked": false,
  "isVisible": true,
  "layerListExpandedType": 0,
  "name": "Path",
  "nameIsFixed": false,
  "pointRadiusBehaviour": 0,
  "points": [
    {
      "_class": "curvePoint",
      "cornerRadius": 0,
      "curveFrom": "{1, 0.97213065627809303}",
      "curveMode": 4,
      "curveTo": "{1, 0.9382679053041646}",
      "hasCurveFrom": true,
      "hasCurveTo": false,
      "point": "{1, 0.9382679053041646}"
    },
    {
      "_class": "curvePoint",
      "cornerRadius": 0,
      "curveFrom": "{0.95433487756452806, 1}",
      "curveMode": 4,
      "curveTo": "{0.97948378557247084, 1}",
      "hasCurveFrom": false,
      "hasCurveTo": true,
      "point": "{0.95433487756452806, 1}"
    },
    {
      "_class": "curvePoint",
      "cornerRadius": 0,
      "curveFrom": "{0.93823075226119523, 1}",
      "curveMode": 1,
      "curveTo": "{0.93823075226119523, 1}",
      "hasCurveFrom": false,
      "hasCurveTo": false,
      "point": "{0.93823075226119523, 1}"
    },
    {
      "_class": "curvePoint",
      "cornerRadius": 0,
      "curveFrom": "{0.061548643282593685, 1}",
      "curveMode": 1,
      "curveTo": "{0.061548643282593685, 1}",
      "hasCurveFrom": false,
      "hasCurveTo": false,
      "point": "{0.061548643282593685, 1}"
    },
    {
      "_class": "curvePoint",
      "cornerRadius": 0,
      "curveFrom": "{0.020295609971324336, 1}",
      "curveMode": 4,
      "curveTo": "{0.045444517979260857, 1}",
      "hasCurveFrom": true,
      "hasCurveTo": false,
      "point": "{0.045444517979260857, 1}"
    },
    {
      "_class": "curvePoint",
      "cornerRadius": 0,
      "curveFrom": "{0, 0.9382679053041646}",
      "curveMode": 4,
      "curveTo": "{0, 0.97213065627809303}",
      "hasCurveFrom": false,
      "hasCurveTo": true,
      "point": "{0, 0.9382679053041646}"
    },
    {
      "_class": "curvePoint",
      "cornerRadius": 0,
      "curveFrom": "{0, 0.34372190590350321}",
      "curveMode": 4,
      "curveTo": "{0, 0.69913095594845553}",
      "hasCurveFrom": true,
      "hasCurveTo": false,
      "point": "{0, 0.69913095594845553}"
    },
    {
      "_class": "curvePoint",
      "cornerRadius": 0,
      "curveFrom": "{0.78844032649460016, 0}",
      "curveMode": 2,
      "curveTo": "{0.21155967350540611, 0}",
      "hasCurveFrom": true,
      "hasCurveTo": true,
      "point": "{0.49988969777189446, 0}"
    },
    {
      "_class": "curvePoint",
      "cornerRadius": 0,
      "curveFrom": "{1, 0.69913095594845553}",
      "curveMode": 4,
      "curveTo": "{1, 0.34372190590350321}",
      "hasCurveFrom": false,
      "hasCurveTo": true,
      "point": "{1, 0.69913095594845553}"
    }
  ],
  "resizingConstraint": 63,
  "resizingType": 0,
  "rotation": 0,
  "shouldBreakMaskChain": false,
  "style": {
    "_class": "style",
    "do_objectID": "151DDA93-44CE-40DE-A666-497964A058CE",
    "endMarkerType": 0,
    "fills": [
      {
        "_class": "fill",
        "color": {
          "_class": "color",
          "alpha": 1,
          "blue": 0.267,
          "green": 0.267,
          "red": 0.267
        },
        "fillType": 0,
        "isEnabled": true,
        "noiseIndex": 0,
        "noiseIntensity": 0,
        "patternFillType": 0,
        "patternTileScale": 1
      }
    ],
    "miterLimit": 10,
    "startMarkerType": 0,
    "windingRule": 1
  }
}