{
  "_class": "shapePath",
  "booleanOperation": -1,
  "clippingMaskMode": 0,
  "do_objectID": "99251D22-C931-40DB-90CE-97A8BB191A06",
  "edited": true,
  "exportOptions": {
    "_class": "exportOptions",
    "do_objectID": "E8FFBF6E-130B-46EF-B897-92B5F47A309A",
    "exportFormats": [
    ],
    "includedLayerIds": [
    ],
    "layerOptions": 0,
    "shouldTrim": false
  },
  "frame": {
    "_class": "rect",
    "constrainProportions": false,
    "do_objectID": "B05CAD00-E1C8-454D-891A-1FA22294476A",
    "height": 0.1,
    "width": 1342,
    "x": 49,
    "y": 2245.2
  },
  "hasClippingMask": false,
  "isClosed": false,
  "isFixedToViewport": false,
  "isFlippedHorizontal": false,
  "isFlippedVertical": false,
  "isLocked": false,
  "isVisible": true,
  "layerListExpandedType": 0,
  "name": "Path 5",
  "nameIsFixed": false,
  "pointRadiusBehaviour": 1,
  "points": [
    {
      "_class": "curvePoint",
      "cornerRadius": 0,
      "curveFrom": "{0, 1.9444444444444602}",
      "curveMode": 1,
      "curveTo": "{0, 1.9444444444444602}",
      "hasCurveFrom": false,
      "hasCurveTo": false,
      "point": "{0, 1.9444444444444602}"
    },
    {
      "_class": "curvePoint",
      "cornerRadius": 0,
      "curveFrom": "{0.47243393998958783, 1.9444444444444442}",
      "curveMode": 1,
      "curveTo": "{0.47243393998958783, 1.9444444444444442}",
      "hasCurveFrom": false,
      "hasCurveTo": false,
      "point": "{0.99962742175856922, 1.9444444444444606}"
    }
  ],
  "resizingConstraint": 63,
  "resizingType": 0,
  "rotation": 0,
  "shouldBreakMaskChain": false,
  "style": {
    "_class": "style",
    "borders": [
      {
        "_class": "border",
        "color": {
          "_class": "color",
          "alpha": 1,
          "blue": 0.592,
          "green": 0.592,
          "red": 0.592
        },
        "fillType": 0,
        "isEnabled": true,
        "position": 0,
        "thickness": 0.25
      }
    ],
    "do_objectID": "A18EAF15-7641-467B-B48D-FBCFC4586BC9",
    "endMarkerType": 0,
    "fills": [
      {
        "_class": "fill",
        "color": {
          "_class": "color",
          "alpha": 1,
          "blue": 0.847,
          "green": 0.847,
          "red": 0.847
        },
        "fillType": 0,
        "isEnabled": false,
        "noiseIndex": 0,
        "noiseIntensity": 0,
        "patternFillType": 1,
        "patternTileScale": 1
      }
    ],
    "miterLimit": 10,
    "startMarkerType": 0,
    "windingRule": 0
  }
}