{
  "_class": "symbolInstance",
  "booleanOperation": -1,
  "clippingMaskMode": 0,
  "do_objectID": "004576C0-6A19-4481-97FC-E2596F678495",
  "exportOptions": {
    "_class": "exportOptions",
    "do_objectID": "D8AFAEAE-1CE1-46FA-8877-1E471184133B",
    "exportFormats": [
    ],
    "includedLayerIds": [
    ],
    "layerOptions": 0,
    "shouldTrim": false
  },
  "frame": {
    "_class": "rect",
    "constrainProportions": true,
    "do_objectID": "EC83415A-1F00-45AB-9CE7-AC1C16F065A0",
    "height": 25,
    "width": 25,
    "x": 22,
    "y": 623
  },
  "hasClippingMask": false,
  "horizontalSpacing": 0,
  "isFixedToViewport": false,
  "isFlippedHorizontal": true,
  "isFlippedVertical": false,
  "isLocked": false,
  "isVisible": true,
  "layerListExpandedType": 0,
  "name": "Icon / Arrow",
  "nameIsFixed": false,
  "overrideValues": [
  ],
  "resizingConstraint": 63,
  "resizingType": 0,
  "rotation": 0,
  "scale": 1,
  "shouldBreakMaskChain": false,
  "style": {
    "_class": "style",
    "do_objectID": "554641B8-BC2E-4B7E-9094-659F5CAF1D54",
    "endMarkerType": 0,
    "miterLimit": 10,
    "startMarkerType": 0,
    "windingRule": 1
  },
  "symbolID": "19B71EAB-FF3B-4405-A6A0-683674FDCEB4",
  "verticalSpacing": 0
}